cashaddress/__init__.py
cashaddress/base58.py
cashaddress/convert.py
cashaddress/crypto.py
tests/__init__.py
tests/test.py
ecashaddress-0.0.1.dist-info/LICENSE
ecashaddress-0.0.1.dist-info/METADATA
ecashaddress-0.0.1.dist-info/WHEEL
ecashaddress-0.0.1.dist-info/top_level.txt
ecashaddress-0.0.1.dist-info/RECORD
